better_json_widget/__init__.py
better_json_widget/apps.py
better_json_widget/py.typed
better_json_widget/static/better_json_widget/js/lib/vue.3.2.26.global.prod.js
better_json_widget/templates/better_json_widget/better_json_widget.html
better_json_widget/widgets.py
django_better_json_widget-0.4.0.dist-info/LICENSE
django_better_json_widget-0.4.0.dist-info/WHEEL
django_better_json_widget-0.4.0.dist-info/METADATA
django_better_json_widget-0.4.0.dist-info/RECORD
