Metadata-Version: 2.1
Name: django-better-json-widget
Version: 0.4.0
Summary: Better JSON Widget for Django Admin
Home-page: https://github.com/yakimka/django-better-json-widget
License: MIT
Author: yakimka
Requires-Python: >=3.8,<4.0
Classifier: Development Status :: 3 - Alpha
Classifier: Environment :: Web Environment
Classifier: Framework :: Django
Classifier: Intended Audience :: Developers
Classifier: License :: OSI Approved :: MIT License
Classifier: Operating System :: OS Independent
Classifier: Programming Language :: Python :: 3
Classifier: Programming Language :: Python :: 3.10
Classifier: Programming Language :: Python :: 3.8
Classifier: Programming Language :: Python :: 3.9
Classifier: Topic :: Software Development :: Libraries :: Python Modules
Project-URL: Repository, https://github.com/yakimka/django-better-json-widget
